be_brief/__init__.py
be_brief/apps.py
be_brief/blocks.py
be_brief/categories.py
be_brief/default_settings.py
be_brief/html_to_text.py
be_brief/model_fields.py
be_brief/model_porter.py
be_brief/models.py
be_brief/side_panels.py
be_brief/views.py
be_brief/wagtail_hooks.py
be_brief/wagtail_settings.py
be_brief/migrations/0001_initial.py
be_brief/migrations/__init__.py
be_brief/templates/be_brief/base_page.html
be_brief/templates/be_brief/post.html
be_brief/templates/be_brief/post_index_page.html
be_brief/templates/be_brief/post_page.html
be_brief/templates/be_brief/blocks/post_authors_block.html
be_brief/templates/be_brief/blocks/post_block.html
be_brief/templates/be_brief/blocks/post_content_stream.html
be_brief/templates/be_brief/blocks/post_dates_block.html
be_brief/templates/be_brief/blocks/post_tags_block.html
be_brief/templates/be_brief/tags/support.html
be_brief/templatetags/__init__.py
be_brief/templatetags/be_brief_tags.py
be_brief-4.1.3.dist-info/AUTHORS.txt
be_brief-4.1.3.dist-info/LICENSE.txt
be_brief-4.1.3.dist-info/METADATA
be_brief-4.1.3.dist-info/WHEEL
be_brief-4.1.3.dist-info/top_level.txt
be_brief-4.1.3.dist-info/zip-safe
be_brief-4.1.3.dist-info/RECORD
