Metadata-Version: 2.1
Name: be-brief
Version: 4.1.3
Summary: A Wagtail app for short form posts.
Home-page: https://github.com/high-dimensional/be-brief
Author: High Dimensional Neurology Group, UCL
Author-email: pypi@highdimensional.net
License: BSD-3-Clause
Platform: any
Classifier: Framework :: Django
Classifier: Framework :: Wagtail
Classifier: Programming Language :: Python :: 3
Classifier: Programming Language :: Python :: 3.8
Classifier: License :: OSI Approved :: BSD License
Classifier: Operating System :: OS Independent
Requires-Python: >=3.8
License-File: LICENSE.txt
License-File: AUTHORS.txt
Requires-Dist: Django (<4.2,>=4.1)
Requires-Dist: wagtail (<4.2,>=4.1)
Requires-Dist: beautifulsoup4 (<4.12,>=4.11)
Requires-Dist: django-auxiliaries (<4.2,>=4.1)
Requires-Dist: js-initiator (<4.2,>=4.1)
Requires-Dist: model-porter (<4.2,>=4.1)
Requires-Dist: wagtail-switch-block (<4.2,>=4.1)
Requires-Dist: wagtail-tags-block (<4.2,>=4.1)
Requires-Dist: wagtail-dynamic-stream-block (<4.2,>=4.1)
Requires-Dist: wagtail-dynamic-choice (<4.2,>=4.1)
Requires-Dist: tour-guide (<4.2,>=4.1)
Requires-Dist: wagtail-synopsis (<4.2,>=4.1)
Requires-Dist: officekit (<4.2,>=4.1)
